dkbotz/__init__.py
dkbotz/imdb.py
dkbotz/translation.py
dkbotz/forcesub/__init__.py
dkbotz/forcesub/forcesub.py
dkbotz/functions/Fonts.py
dkbotz/functions/TimeFormatter.py
dkbotz/functions/__init__.py
dkbotz/functions/check_gap.py
dkbotz/functions/clean.py
dkbotz/functions/cult_small_video.py
dkbotz/functions/fix_ext.py
dkbotz/functions/generate_screen_shots.py
dkbotz/functions/get_duration.py
dkbotz/functions/get_file_id.py
dkbotz/functions/get_size.py
dkbotz/functions/humanbytes.py
dkbotz/functions/isdownloadable_link.py
dkbotz/functions/split_list.py
dkbotz/functions/streamtape.py
dkbotz/functions/take_screen_shot.py
dkbotz/remove_tag/__init__.py
dkbotz/remove_tag/remove_tag.py
dkbotz-1.4.0.dist-info/LICENSE
dkbotz-1.4.0.dist-info/METADATA
dkbotz-1.4.0.dist-info/WHEEL
dkbotz-1.4.0.dist-info/top_level.txt
dkbotz-1.4.0.dist-info/RECORD
