Metadata-Version: 2.1
Name: dkbotz
Version: 1.4.0
Summary: Package containing basic functions to build telegram bots.
Home-page: https://github.com/DKBOTZNETWORK
Author: DK BOTZ
License: GNU AFFERO GENERAL PUBLIC LICENSE (v3)
Classifier: Programming Language :: Python :: 3
Classifier: Programming Language :: Python :: 3.6
Classifier: Programming Language :: Python :: 3.7
Classifier: Programming Language :: Python :: 3.8
Classifier: Programming Language :: Python :: 3.9
Classifier: License :: OSI Approved :: GNU General Public License v3 (GPLv3)
Classifier: Operating System :: OS Independent
Requires-Python: >=3.6
License-File: LICENSE
Requires-Dist: pyrogram
Requires-Dist: requests
Requires-Dist: aiohttp
Requires-Dist: gTTS
Requires-Dist: TgCrypto
Requires-Dist: googletrans (==3.1.0a0)
Requires-Dist: ffmpeg
Requires-Dist: hachoir
Requires-Dist: psutil
Requires-Dist: humanfriendly
Requires-Dist: aiofiles
